pycodb/__init__.py
pycodb/entities/__init__.py
pycodb/entities/basetable.py
pycodb/entities/database.py
pycodb/entities/dataproxy.py
pycodb-0.1.0.dist-info/METADATA
pycodb-0.1.0.dist-info/WHEEL
pycodb-0.1.0.dist-info/RECORD
